aprsd_timeopencage_plugin/__init__.py
aprsd_timeopencage_plugin/aprsd_timeopencage_plugin.py
aprsd_timeopencage_plugin/conf/__init__.py
aprsd_timeopencage_plugin/conf/opts.py
aprsd_timeopencage_plugin/conf/time.py
aprsd_timeopencage_plugin-0.2.0.dist-info/LICENSE
aprsd_timeopencage_plugin-0.2.0.dist-info/METADATA
aprsd_timeopencage_plugin-0.2.0.dist-info/WHEEL
aprsd_timeopencage_plugin-0.2.0.dist-info/entry_points.txt
aprsd_timeopencage_plugin-0.2.0.dist-info/pbr.json
aprsd_timeopencage_plugin-0.2.0.dist-info/top_level.txt
aprsd_timeopencage_plugin-0.2.0.dist-info/RECORD
