Metadata-Version: 2.1
Name: aprsd-timeopencage-plugin
Version: 0.2.0
Summary: APRSD plugin for fetching time based on GPS location
Author: Walter A. Boring IV
Author-email: waboring@hemna.com
License: Apache-2.0
Classifier: Topic :: Communications :: Ham Radio
Classifier: Operating System :: POSIX :: Linux
Classifier: Programming Language :: Python
Classifier: Programming Language :: Python :: 3.7
Classifier: Programming Language :: Python :: 3.8
Classifier: Programming Language :: Python :: 3.9
License-File: LICENSE
Requires-Dist: pbr
Requires-Dist: aprsd (>=3.0.0)
Requires-Dist: opencage
Requires-Dist: pytz
